tests/__init__.py
tests/conftest.py
tests/test_expose.py
tests/test_expose_with_identity.py
tests/test_expose_with_transaction.py
tests/test_expose_with_validate.py
tests/test_resource_exception_handling.py
tests/test_resource_init_exception_handling.py
tests/test_rest.py
tests/test_validate.py
turbogears/__init__.py
turbogears/config.py
turbogears/controllers.py
turbogears/decorator.py
turbogears/dispatchers.py
turbogears/docgen.py
turbogears/errorhandling.py
turbogears/filters.py
turbogears/finddata.py
turbogears/hooks.py
turbogears/release.py
turbogears/scheduler.py
turbogears/startup.py
turbogears/testutil.py
turbogears/util.py
turbogears/validators.py
turbogears/command/__init__.py
turbogears/command/base.py
turbogears/command/i18n.py
turbogears/command/info.py
turbogears/command/kid2genshi.py
turbogears/command/sacommand.py
turbogears/database/__init__.py
turbogears/database/sqlalchemy_support.py
turbogears/i18n/__init__.py
turbogears/i18n/format.py
turbogears/i18n/kidutils.py
turbogears/i18n/tg_gettext.py
turbogears/i18n/utils.py
turbogears/i18n/data/TurboGears.pot
turbogears/i18n/data/__init__.py
turbogears/i18n/data/af.py
turbogears/i18n/data/af_ZA.py
turbogears/i18n/data/am.py
turbogears/i18n/data/am_ET.py
turbogears/i18n/data/ar.py
turbogears/i18n/data/ar_AE.py
turbogears/i18n/data/ar_BH.py
turbogears/i18n/data/ar_DZ.py
turbogears/i18n/data/ar_EG.py
turbogears/i18n/data/ar_IN.py
turbogears/i18n/data/ar_IQ.py
turbogears/i18n/data/ar_JO.py
turbogears/i18n/data/ar_KW.py
turbogears/i18n/data/ar_LB.py
turbogears/i18n/data/ar_LY.py
turbogears/i18n/data/ar_MA.py
turbogears/i18n/data/ar_OM.py
turbogears/i18n/data/ar_QA.py
turbogears/i18n/data/ar_SA.py
turbogears/i18n/data/ar_SD.py
turbogears/i18n/data/ar_SY.py
turbogears/i18n/data/ar_TN.py
turbogears/i18n/data/ar_YE.py
turbogears/i18n/data/be.py
turbogears/i18n/data/be_BY.py
turbogears/i18n/data/bg.py
turbogears/i18n/data/bg_BG.py
turbogears/i18n/data/bn.py
turbogears/i18n/data/bn_IN.py
nitrous-1.0.0.dist-info/LICENSE.txt
nitrous-1.0.0.dist-info/METADATA
nitrous-1.0.0.dist-info/WHEEL
nitrous-1.0.0.dist-info/dependency_links.txt
nitrous-1.0.0.dist-info/entry_points.txt
nitrous-1.0.0.dist-info/top_level.txt
nitrous-1.0.0.dist-info/RECORD
