Metadata-Version: 2.2
Name: Nitrous
Version: 1.0.0
Summary: Nitrous gives TurboGears 1 a boost
Home-page: https://bitbucket.org/brightlinkinfrastructure/nitrous
Download-URL: https://bitbucket.org/brightlinkinfrastructure/nitrous/get/v1.0.0.tar.gz
Author: BrightLink
Author-email: drocco@thebrightlink.com
Maintainer: BrightLink
Maintainer-email: drocco@thebrightlink.com
License: MIT
Classifier: Development Status :: 3 - Alpha
Classifier: Environment :: Console
Classifier: Framework :: TurboGears
Classifier: Intended Audience :: Developers
Classifier: License :: OSI Approved :: MIT License
Classifier: Operating System :: OS Independent
Classifier: Programming Language :: Python
Classifier: Programming Language :: Python :: 3.7
Classifier: Topic :: Internet :: WWW/HTTP
Classifier: Topic :: Software Development :: Libraries :: Python Modules
License-File: LICENSE.txt
Requires-Dist: attr>=0.3.2
Requires-Dist: attrs>=19.0.0
Requires-Dist: CherryPy>=3.1.2
Requires-Dist: ConfigObj>=4.3.2
Requires-Dist: FormEncode>=1.3.0
Requires-Dist: future>=0.17.1
Requires-Dist: Genshi>=0.4.4
Requires-Dist: simplejson>=3.17.0
Requires-Dist: sqlalchemy<1.4.0
Requires-Dist: TGScheduler>=1.6.2
Provides-Extra: dev
Requires-Dist: pytest>=8.2.1; extra == "dev"
Requires-Dist: WebTest>=3.0.0; extra == "dev"
Dynamic: author
Dynamic: author-email
Dynamic: classifier
Dynamic: description
Dynamic: download-url
Dynamic: home-page
Dynamic: license
Dynamic: maintainer
Dynamic: maintainer-email
Dynamic: provides-extra
Dynamic: requires-dist
Dynamic: summary
